spheres/__init__.py
spheres/beams.py
spheres/coordinates.py
spheres/oscillators.py
spheres/relativity.py
spheres/symmetrization.py
spheres/symplectic.py
spheres/utils.py
spheres/polyhedra/__init__.py
spheres/spin_circuits/__init__.py
spheres/spin_circuits/pytket.py
spheres/spin_circuits/qiskit.py
spheres/spin_circuits/strawberryfields.py
spheres/stabilization/__init__.py
spheres/stabilization/pytket.py
spheres/stars/__init__.py
spheres/stars/mixed.py
spheres/stars/pure.py
spheres/stars/star_utils.py
spheres/visualization/__init__.py
spheres/visualization/majorana_sphere.py
spheres/visualization/matplotlib_spheres.py
spheres/visualization/operator_sphere.py
spheres/visualization/schwinger_spheres.py
spheres/visualization/vp_object.py
spheres-0.3.0.9.dist-info/LICENSE
spheres-0.3.0.9.dist-info/METADATA
spheres-0.3.0.9.dist-info/WHEEL
spheres-0.3.0.9.dist-info/top_level.txt
spheres-0.3.0.9.dist-info/RECORD
