Metadata-Version: 2.1
Name: spheres
Version: 0.3.0.9
Summary: toolbox for higher spin and symmetrization
Home-page: https://github.com/heyredhat/spheres
Author: Matthew Weiss
Author-email: heyredhat@gmail.com
License: UNKNOWN
Platform: UNKNOWN
Classifier: Programming Language :: Python :: 3
Classifier: License :: OSI Approved :: MIT License
Classifier: Operating System :: OS Independent
Requires-Python: >=3.6
Requires-Dist: numpy
Requires-Dist: qutip
Requires-Dist: matplotlib
Requires-Dist: vpython
Requires-Dist: sympy
Requires-Dist: quadpy
Requires-Dist: pytket
Requires-Dist: pytket-qiskit
Requires-Dist: qiskit
Requires-Dist: strawberryfields
